django_gae_backends-1.0.dist-info/DESCRIPTION.rst
django_gae_backends-1.0.dist-info/WHEEL
django_gae_backends-1.0.dist-info/top_level.txt
django_gae_backends-1.0.dist-info/RECORD
django_gae_backends-1.0.dist-info/metadata.json
django_gae_backends-1.0.dist-info/METADATA
gae_backends/__init__.py
gae_backends/mail.py
gae_backends/test_helpers.py
gae_backends/memcache.py
gae_backends/sessions/__init__.py
gae_backends/sessions/models.py
gae_backends/sessions/db.py
gae_backends/sessions/cached_db.py
