Metadata-Version: 2.0
Name: django-gae-backends
Version: 1.0
Summary: UNKNOWN
Home-page: https://github.com/rodrigorodriguescosta/django-gae-backends
Author: Rodrigo Rodrigues
Author-email: rodrigorodriguescosta@gmail.com
License: MIT
Platform: UNKNOWN
Classifier: Development Status :: 4 - Beta
Classifier: Intended Audience :: Developers
Classifier: Topic :: Software Development :: Build Tools
Classifier: License :: OSI Approved :: MIT License
Classifier: Programming Language :: Python :: 2
Classifier: Programming Language :: Python :: 2.6
Classifier: Programming Language :: Python :: 2.7
Classifier: Programming Language :: Python :: 3
Classifier: Programming Language :: Python :: 3.3
Classifier: Programming Language :: Python :: 3.4
Classifier: Programming Language :: Python :: 3.5
Requires-Dist: django
Requires-Dist: requests
